{
  "schema_version": 2,
  "max_iterations": 10,
  "current_iteration": 0,
  "stop_conditions": [
    "definition_of_done_met",
    "blocked",
    "human_review_required",
    "max_iterations_reached"
  ],
  "human_review_gates": [
    "before executing destructive operations",
    "before changing architecture or security boundaries",
    "before declaring completion"
  ],
  "last_run_time": "2026-07-17T11:26:00Z",
  "completion_status": "track_a_complete_track_c_research_done",
  "should_continue": false,
  "pause_reason": "Supervised step 2026-07-17: Track C unit 10 done — truck-stop data-source research documented in docs/truck-stop-data-sources.md (search-excerpt evidence; V1-V5 full-text verification worklist). Paused at human_review_gate: Track C unit 11 needs owner approval of the sourcing plan; Track B still behind foundation approval + flagged-item verification; device/UI reviews and release publication remain owner gates.",
  "execution": {
    "enabled": false,
    "preflight_confirmed": true,
    "preflight_confirmed_at": "2026-07-16T23:10:44Z",
    "preflight_confirmed_by": "owner (jackofall1232) via EXECUTE (resumed run) in session 21c431a0",
    "max_iterations": 25,
    "current_iteration": 3,
    "last_run_boundary": "human_review_gate",
    "iterations_since_progress": 0,
    "last_progress_iteration": 3,
    "no_progress_threshold": 3,
    "run_boundaries": [
      "definition_of_done_met",
      "iteration_limit_reached",
      "human_review_gate",
      "destructive_operation_required",
      "ambiguous_requirements",
      "unfixable_failing_tests",
      "missing_secrets_or_credentials",
      "lock_lease_conflict",
      "stop_signal"
    ]
  }
}
